yapp/__init__.py
yapp/cmd.py
yapp/family_phaser.py
yapp/fphtrain.py
yapp/gamete.py
yapp/lmm.py
yapp/mendel.py
yapp/origins.py
yapp/pedigree.py
yapp/recombination.py
yapp/sperm.py
yapp/vcf.py
yapp/wcsp.py
yappgen-0.4.4.dist-info/licenses/LICENSE
yappgen-0.4.4.dist-info/METADATA
yappgen-0.4.4.dist-info/WHEEL
yappgen-0.4.4.dist-info/entry_points.txt
yappgen-0.4.4.dist-info/top_level.txt
yappgen-0.4.4.dist-info/RECORD
