Metadata-Version: 2.4
Name: yappgen
Version: 0.4.4
Summary: Yet Another Phasing Program
License-Expression: LGPL-2.1-only
Project-URL: Repository, https://github.com/BertrandServin/yapp
Project-URL: Documentation, https://yapp.readthedocs.io
Requires-Python: >3.7
License-File: LICENSE
Requires-Dist: numpy>=2
Requires-Dist: scipy
Requires-Dist: cyvcf2>=0.30.4
Requires-Dist: zarr<4,>=3.1
Requires-Dist: h5py>=3.2.1
Requires-Dist: fastphase>=2.0.2
Requires-Dist: numba>=0.53.1
Requires-Dist: pytoulbar2
Requires-Dist: rich
Dynamic: license-file
